grab_screen/__init__.py
grab_screen/__main__.py
grab_screen/cli.py
grab_screen/exceptions.py
grab_screen/images.py
grab_screen/screen.py
grab_screen/utils.py
grab_screen/version.py
grab_screen/conf/__init__.py
grab_screen/conf/configs.py
grab_screen/conf/default.ini
grab_screen/storages/__init__.py
grab_screen/storages/base.py
grab_screen/storages/cloudapp.py
grab_screen-0.0.13.dist-info/DESCRIPTION.rst
grab_screen-0.0.13.dist-info/METADATA
grab_screen-0.0.13.dist-info/RECORD
grab_screen-0.0.13.dist-info/WHEEL
grab_screen-0.0.13.dist-info/entry_points.txt
grab_screen-0.0.13.dist-info/metadata.json
grab_screen-0.0.13.dist-info/top_level.txt
